{
  "Cinthia Samylle Martins Souza da Silva": [
    {
      "nome": "Paulo ítalo de Oliveira",
      "classificacao": "Assistente"
    },
    {
      "nome": "Fernando Gabriel Noronha Nascimento",
      "classificacao": "Assistente"
    },
    {
      "nome": "Hellen Sthefane Dos Santos Fernandes",
      "classificacao": "Advogado Recursal"
    },
    {
      "nome": "Alyssa Geórgia Bezerra e Silva",
      "classificacao": "Advogado Recursal"
    },
    {
      "nome": "Michael Henrique Borges Fonseca Rodrigues",
      "classificacao": "Assistente Recursal"
    },
    {
      "nome": "Carlos Eduardo de Almeida Bezerra",
      "classificacao": "Assistente Recursal"
    },
{
      "nome": "Priscila Cartonilho de Souza Ramos",
      "classificacao": "Controladoria"
    }
  ],
  "Arthur Augusto Alves de Almeida": [
    {
      "nome": "Jennifer Camile Macedo Rodrigues",
      "classificacao": "Assistente"
    },
    {
      "nome": "Breno Medeiros de Andrade",
      "classificacao": "Assistente"
    },
    {
      "nome": "Alyssa Geórgia Bezerra e Silva",
      "classificacao": "Advogado Recursal"
    },
    {
      "nome": "Michael Henrique Borges Fonseca Rodrigues",
      "classificacao": "Assistente Recursal"
    },
    {
      "nome": "Carlos Eduardo de Almeida Bezerra",
      "classificacao": "Assistente Recursal"
    },
{
      "nome": "Priscila Cartonilho de Souza Ramos",
      "classificacao": "Controladoria"
    }
  ],
  "Enzo Pinto Bagatoli Carriço": [
    {
      "nome": "Amanda Simões Costa da Silva",
      "classificacao": "Assistente"
    },
    {
      "nome": "Gabriel Abner Alves De Pontes",
      "classificacao": "Assistente"
    },
    {
      "nome": "Hellen Sthefane Dos Santos Fernandes",
      "classificacao": "Advogado Recursal"
    },
    {
      "nome": "Michael Henrique Borges Fonseca Rodrigues",
      "classificacao": "Assistente Recursal"
    },
    {
      "nome": "Carlos Eduardo de Almeida Bezerra",
      "classificacao": "Assistente Recursal"
    },
{
      "nome": "Priscila Cartonilho de Souza Ramos",
      "classificacao": "Controladoria"
    }
  ],
  "Christiane Serejo Cardoso": [
    {
      "nome": "Yasmin Karoline Bezerra Moura",
      "classificacao": "Assistente"
    },
    {
      "nome": "Tayná Costa Souza",
      "classificacao": "Assistente"
    },
    {
      "nome": "José Leonardo de Araújo Jales",
      "classificacao": "Advogado Recursal"
    },
    {
      "nome": "Débora Regina Azevedo de Oliveira",
      "classificacao": "Assistente Recursal"
    },
    {
      "nome": "Carlos Eduardo de Almeida Bezerra",
      "classificacao": "Assistente Recursal"
    },
{
      "nome": "Priscila Cartonilho de Souza Ramos",
      "classificacao": "Controladoria"
    }
  ],
  "Danielle Costa Alves": [
    {
      "nome": "Yasmin de Menezes Dantas",
      "classificacao": "Assistente"
    },
    {
      "nome": "José Leonardo de Araújo Jales",
      "classificacao": "Advogado Recursal"
    },
    {
      "nome": "Gabriel Carvalho Rodrigues de Oliveira",
      "classificacao": "Advogado Recursal"
    },
    {
      "nome": "Débora Regina Azevedo de Oliveira",
      "classificacao": "Assistente Recursal"
    },
    {
      "nome": "Carlos Eduardo de Almeida Bezerra",
      "classificacao": "Assistente Recursal"
    },
{
      "nome": "Priscila Cartonilho de Souza Ramos",
      "classificacao": "Controladoria"
    }
  ],
  "Mikaelle Thaisa da Costa": [
    {
      "nome": "Isabella Ferreira Barbalho Borja",
      "classificacao": "Assistente"
    },
    {
      "nome": "Antônio Uemerson de Carvalho",
      "classificacao": "Advogado Recursal"
    },
    {
      "nome": "Alexandre Victor da Silva Lima",
      "classificacao": "Assistente Recursal"
    }
  ],
  "Melissa Cristine de Oliveira e Santos": [
    {
      "nome": "Mateus Brito de Brito",
      "classificacao": "Assistente"
    },
    {
      "nome": "Ana Carolina Viana Nascimento",
      "classificacao": "Advogado Recursal"
    },
    {
      "nome": "Alexandre Victor da Silva Lima",
      "classificacao": "Assistente Recursal"
    }
  ],
  "Andrielly Duarte de Farias": [
    {
      "nome": "Luana de Araujo Alves",
      "classificacao": "Assistente"
    },
    {
      "nome": "Algacy Chaves de Almeida Júnior",
      "classificacao": "Advogado Recursal"
    },
    {
      "nome": "Alexandre Victor da Silva Lima",
      "classificacao": "Assistente Recursal"
    }
  ],
  "Michelle Dantas Ferreira": [
    {
      "nome": "Maria Eduarda Guedes Cavalcante",
      "classificacao": "Assistente"
    },
    {
      "nome": "Antônio Uemerson de Carvalho",
      "classificacao": "Advogado Recursal"
    },
    {
      "nome": "Alexandre Victor da Silva Lima",
      "classificacao": "Assistente Recursal"
    }
  ],
  "Maria Gabrielly Silva Rodrigues": [
    {
      "nome": "Marilia Gabriela Andrade Freitas",
      "classificacao": "Assistente"
    },
    {
      "nome": "Algacy Chaves de Almeida Júnior",
      "classificacao": "Advogado Recursal"
    },
    {
      "nome": "Alexandre Victor da Silva Lima",
      "classificacao": "Assistente Recursal"
    }
  ],
  "Vitoria Machado Domingo": [
    {
      "nome": "Paulo Fernando Cisneiro da Costa Reis",
      "classificacao": "Assistente"
    },
    {
      "nome": "Ana Carolina Viana Nascimento",
      "classificacao": "Advogado Recursal"
    },
    {
      "nome": "Alexandre Victor da Silva Lima",
      "classificacao": "Assistente Recursal"
    }
  ]
}